{
  "_comment": "Hindi intent config for the analyzer. patterns override the English trigger regexes (analyzer.py); absent keys fall back to English. Built by scripts/build_analyzer_lang.py. See internal-docs/multilingual-unlock-plan.md.",
  "stopwords": [
    "का",
    "के",
    "की",
    "में",
    "से",
    "को",
    "पर",
    "और",
    "या",
    "है",
    "हैं",
    "था",
    "थे",
    "थी",
    "क्या",
    "कौन",
    "कब",
    "कहाँ",
    "कैसे",
    "क्यों",
    "यह",
    "वह",
    "ये",
    "वे",
    "जो",
    "जब",
    "तक",
    "एक",
    "इस",
    "उस",
    "ने",
    "भी",
    "नहीं",
    "हाँ",
    "बहुत",
    "अधिक",
    "लिए",
    "साथ",
    "बिना",
    "ऊपर",
    "नीचे",
    "बीच",
    "मैं",
    "तुम",
    "आप",
    "हम",
    "कि",
    "तो",
    "ही",
    "अपने",
    "अपना",
    "उन",
    "इन",
    "कोई",
    "कुछ"
  ],
  "topic_stopwords": [
    "सब",
    "सभी",
    "कुछ",
    "कोई",
    "यह",
    "वह",
    "एक",
    "इस",
    "उस"
  ],
  "relation_map": {
    "पिता": "father-of-rev",
    "माता": "mother-of-rev",
    "माँ": "mother-of-rev",
    "माता-पिता": "father-of-rev",
    "पुत्र": "father-of",
    "बेटा": "father-of",
    "पुत्री": "father-of",
    "बेटी": "father-of",
    "भाई": "sibling-of",
    "बहन": "sibling-of",
    "पति": "partner-of",
    "पत्नी": "partner-of"
  },
  "patterns": {
    "topic": "बाइबल\\s+(.+?)\\s+(?:के\\s+बारे\\s+में|के\\s+विषय\\s+में)\\s+क्या\\s+(?:कहती|बताती)\\s+है|(.+?)\\s+(?:के\\s+बारे\\s+में|के\\s+विषय\\s+में)\\s+(?:आयतें|वचन|पद|शास्त्र)",
    "entity": [
      "^\\s*(['\\\"]?)([^\\s\\d_.,:;!?()\\[\\]{}«»\\\"'“”’/\\\\।॥]+)\\1\\s+कौन\\s+(?:है|था|थी|हैं|थे)\\s*\\??\\s*$",
      "^\\s*(['\\\"]?)([^\\s\\d_.,:;!?()\\[\\]{}«»\\\"'“”’/\\\\।॥]+)\\1\\s+क्या\\s+(?:है|था|थी|हैं)\\s*\\??\\s*$",
      "^\\s*(['\\\"]?)([^\\s\\d_.,:;!?()\\[\\]{}«»\\\"'“”’/\\\\।॥]+)\\1\\s+(?:का|के)\\s+(?:अर्थ|मतलब)\\s+क्या\\s+है\\s*\\??\\s*$",
      "^\\s*(['\\\"]?)([^\\s\\d_.,:;!?()\\[\\]{}«»\\\"'“”’/\\\\।॥]+)\\1\\s+के\\s+बारे\\s+में\\s+(?:बताओ|बताइए|बताएं)\\s*\\??\\s*$"
    ],
    "xref": "(.+?)\\s+के\\s+लिए\\s+(?:क्रॉस[- ]?रेफरेंस|पारस्परिक\\s+संदर्भ)|(.+?)\\s+(?:से\\s+संबंधित|के\\s+समानांतर)\\s+(?:आयतें|वचन|अंश|पद)",
    "genealogy_possessive": "([^\\s\\d_.,:;!?()\\[\\]{}«»\\\"'“”’/\\\\।॥]+)\\s+(?:का|के|की)\\s+(माता-पिता|पिता|माता|माँ|पुत्र|बेटा|पुत्री|बेटी|भाई|बहन|पति|पत्नी)"
  }
}
